<?xml version="1.0"?>
<RECYCLEDDATA>
<DATA type="MIF" src="image1.jpg" size="44980" crc="509885557" ref="image1.mif" ref_size="333960" ref_crc="2320870527">
</DATA>
<DATA type="MIF" src="image2.jpg" size="115670" crc="3256734398" ref="image2.mif" ref_size="104174" ref_crc="3792030054">
</DATA>
<DATA type="MIF" src="image3.jpg" size="13456" crc="1223944800" ref="image3.mif" ref_size="121870" ref_crc="2365134912">
</DATA>
<DATA type="MIF" src="image4.jpg" size="49271" crc="3288002194" ref="image4.mif" ref_size="30120" ref_crc="608225950">
</DATA>
</RECYCLEDDATA>
